django_sh/__init__.py
django_sh/asgi.py
django_sh/settings.py
django_sh/urls.py
django_sh/wsgi.py
sh/__init__.py
sh/admin.py
sh/apps.py
sh/auth_function_default.py
sh/constants.py
sh/decorators.py
sh/forms.py
sh/functions.py
sh/models.py
sh/tests.py
sh/urls.py
sh/utils_views.py
sh/views.py
sh/management/__init__.py
sh/management/commands/__init__.py
sh/management/commands/clear_commands.py
sh/migrations/0001_initial.py
sh/migrations/0002_auto_20210830_2111.py
sh/migrations/0003_savedcommand.py
sh/migrations/0004_savedcommand_description.py
sh/migrations/0005_auto_20210915_1750.py
sh/migrations/0006_command_error.py
sh/migrations/0007_auto_20210921_2202.py
sh/migrations/0008_shellsettings_auth_function.py
sh/migrations/__init__.py
sh/static/sh/codemirror/.editorconfig
sh/static/sh/codemirror/.gitattributes
sh/static/sh/codemirror/.npmignore
sh/static/sh/codemirror/.travis.yml
sh/static/sh/codemirror/AUTHORS
sh/static/sh/codemirror/CHANGELOG.md
sh/static/sh/codemirror/CONTRIBUTING.md
sh/static/sh/codemirror/LICENSE
sh/static/sh/codemirror/README.md
sh/static/sh/codemirror/index.html
sh/static/sh/codemirror/package.json
sh/static/sh/codemirror/rollup.config.js
sh/static/sh/codemirror/.github/ISSUE_TEMPLATE.md
sh/static/sh/codemirror/.github/PULL_REQUEST_TEMPLATE.md
sh/static/sh/codemirror/addon/comment/comment.js
sh/static/sh/codemirror/addon/comment/continuecomment.js
sh/static/sh/codemirror/addon/dialog/dialog.css
sh/static/sh/codemirror/addon/dialog/dialog.js
sh/static/sh/codemirror/addon/display/autorefresh.js
sh/static/sh/codemirror/addon/display/fullscreen.css
sh/static/sh/codemirror/addon/display/fullscreen.js
sh/static/sh/codemirror/addon/display/panel.js
sh/static/sh/codemirror/addon/display/placeholder.js
sh/static/sh/codemirror/addon/display/rulers.js
sh/static/sh/codemirror/addon/edit/closebrackets.js
sh/static/sh/codemirror/addon/edit/closetag.js
sh/static/sh/codemirror/addon/edit/continuelist.js
sh/static/sh/codemirror/addon/edit/matchbrackets.js
django_sh-1.0.28.dist-info/METADATA
django_sh-1.0.28.dist-info/WHEEL
django_sh-1.0.28.dist-info/top_level.txt
django_sh-1.0.28.dist-info/RECORD
