Metadata-Version: 2.1
Name: django-sh
Version: 1.0.28
Summary: Django shell app for browser
Home-page: https://gitlab.com/jahazieldom/django-sh
Author: admintotal-dev
License: UNKNOWN
Platform: UNKNOWN
Requires-Dist: django (>=1.8) ; python_version >= "3"
